pyswashes/__init__.py
pyswashes/pyswashes.py
pyswashes-0.1.0.dist-info/DESCRIPTION.rst
pyswashes-0.1.0.dist-info/METADATA
pyswashes-0.1.0.dist-info/RECORD
pyswashes-0.1.0.dist-info/WHEEL
pyswashes-0.1.0.dist-info/metadata.json
pyswashes-0.1.0.dist-info/top_level.txt
