Metadata-Version: 2.0
Name: pyswashes
Version: 0.1.0
Summary: a Python interface for SWASHES
Home-page: UNKNOWN
Author: Laurent Courty
Author-email: laurent@courty.me
License: GPLv3
Keywords: science engineering hydraulics
Platform: UNKNOWN
Classifier: Development Status :: 2 - Pre-Alpha
Classifier: Intended Audience :: Science/Research
Classifier: License :: OSI Approved :: GNU General Public License v3 (GPLv3)
Classifier: Operating System :: OS Independent
Classifier: Programming Language :: Python :: 3.6
Classifier: Topic :: Scientific/Engineering
Requires-Dist: pandas
